subway_detector/__init__.py
subway_detector/config.py
subway_detector/data.py
subway_detector/detector.py
subway_detector/class_2/__init__.py
subway_detector/class_2/class_2_model.py
subway_detector/class_2/net.py
subway_detector/class_n/__init__.py
subway_detector/class_n/class_n_model.py
subway_detector/class_n/net.py
subway_detector/detec/__init__.py
subway_detector/detec/dete.py
subway_detector/detec/nms_iou.py
subwaydetec-0.0.4.dist-info/DESCRIPTION.rst
subwaydetec-0.0.4.dist-info/METADATA
subwaydetec-0.0.4.dist-info/RECORD
subwaydetec-0.0.4.dist-info/WHEEL
subwaydetec-0.0.4.dist-info/entry_points.txt
subwaydetec-0.0.4.dist-info/metadata.json
subwaydetec-0.0.4.dist-info/top_level.txt
